pytest_pop/plugin.py
pytest_pop/mods/testing.py
pytest_pop-12.0.0.dist-info/LICENSE
pytest_pop-12.0.0.dist-info/METADATA
pytest_pop-12.0.0.dist-info/WHEEL
pytest_pop-12.0.0.dist-info/entry_points.txt
pytest_pop-12.0.0.dist-info/top_level.txt
pytest_pop-12.0.0.dist-info/RECORD
