Metadata-Version: 2.1
Name: pytest-pop
Version: 12.0.0
Summary: A pytest plugin to help with testing pop projects
Home-page: https://gitlab.com/vmware/pop/pytest-pop
Author: Tyler Johnson
Author-email: tjohnson@saltstack.com
License: UNKNOWN
Platform: UNKNOWN
Classifier: Framework :: Pytest
Classifier: Intended Audience :: Developers
Classifier: Topic :: Software Development :: Testing
Classifier: Operating System :: OS Independent
Classifier: Programming Language :: Python
Classifier: Programming Language :: Python :: 3.8
Classifier: Programming Language :: Python :: 3.9
Classifier: Programming Language :: Python :: 3.10
Classifier: Programming Language :: Python :: 3.11
Classifier: Development Status :: 5 - Production/Stable
Requires-Python: >=3.8
License-File: LICENSE
Requires-Dist: mock
Requires-Dist: nest-asyncio
Requires-Dist: pytest
Requires-Dist: pytest-async
Requires-Dist: pytest-asyncio (<0.19,>=0.17)
Requires-Dist: pop (>=19.0.0)
Requires-Dist: dict-toolbox (>=2.2.0)
Requires-Dist: pop-config (>=9.0.0)
